docker_lite_python/__init__.py
docker_lite_python/docker_lite.py
docker_lite_python/test_docker_lite.py
docker_lite_python-1.0.6.dist-info/LICENSE.txt
docker_lite_python-1.0.6.dist-info/METADATA
docker_lite_python-1.0.6.dist-info/WHEEL
docker_lite_python-1.0.6.dist-info/top_level.txt
docker_lite_python-1.0.6.dist-info/RECORD
