Metadata-Version: 2.1
Name: docker-lite-python
Version: 1.0.6
Summary: Sandbox running code in Docker.
Home-page: https://github.com/jeff-vincent/docker-lite-python
Author: Jeff Vincent
Author-email: jeff.d.vincent@gmail.com
License: MIT
Platform: UNKNOWN
Classifier: License :: OSI Approved :: MIT License
Classifier: Programming Language :: Python :: 3
Classifier: Programming Language :: Python :: 3.7
Requires-Dist: docker
